foo_parameterization/__init__.py
foo_parameterization/foo_parameterization.py
foo_parameterization/tests/__init__.py
foo_parameterization/tests/test_foo_parameterization.py
foo_parameterization-0.1.dist-info/LICENSE
foo_parameterization-0.1.dist-info/METADATA
foo_parameterization-0.1.dist-info/WHEEL
foo_parameterization-0.1.dist-info/top_level.txt
foo_parameterization-0.1.dist-info/RECORD
