Metadata-Version: 2.1
Name: foo-parameterization
Version: 0.1
Summary: Calculates the Foo et al. parameterization for atmospheric sea-spray physics
Home-page: https://github.com/bourque/foo_parameterization.git
Author: Matthew Bourque
Author-email: matthewkbourque@gmail.com
License: BSD 3-Clause
Keywords: python
Platform: UNKNOWN
Classifier: Programming Language :: Python
License-File: LICENSE
Requires-Dist: pytest
